commisery/__init__.py
commisery/checking.py
commisery/commit.py
commisery/github.py
commisery/hopic_template.py
commisery/range.py
commisery/cli/__init__.py
commisery-0.10.0.dist-info/LICENSE
commisery-0.10.0.dist-info/METADATA
commisery-0.10.0.dist-info/WHEEL
commisery-0.10.0.dist-info/entry_points.txt
commisery-0.10.0.dist-info/top_level.txt
commisery-0.10.0.dist-info/zip-safe
commisery-0.10.0.dist-info/RECORD
