Metadata-Version: 2.1
Name: commisery
Version: 0.10.0
Summary: Commisery is a package to help check whether given commit messages adhere to Conventional Commits. Specifically, it checks the syntax and some small aspects of the semantics.
Home-page: https://github.com/tomtom-international/commisery
Author: TomTom N.V.
License: Apache License 2.0
Project-URL: Source Code, https://github.com/tomtom-international/commisery
Platform: UNKNOWN
Classifier: License :: OSI Approved :: Apache Software License
Requires-Python: >=3.6.5
License-File: LICENSE
Requires-Dist: click (<9,>=7.1.2)
Requires-Dist: click-log
Requires-Dist: GitPython (<4,>=3)
Requires-Dist: regex
Requires-Dist: stemming (<2,>=1)
Provides-Extra: github
Requires-Dist: PyGithub (<2,>=1.53) ; extra == 'github'
